k2flix/__init__.py
k2flix/core.py
k2flix/crawler.py
k2flix-1.0.0.dist-info/entry_points.txt
k2flix-1.0.0.dist-info/RECORD
k2flix-1.0.0.dist-info/WHEEL
k2flix-1.0.0.dist-info/DESCRIPTION.rst
k2flix-1.0.0.dist-info/top_level.txt
k2flix-1.0.0.dist-info/metadata.json
k2flix-1.0.0.dist-info/METADATA
