Metadata-Version: 2.0
Name: k2flix
Version: 1.0.0
Summary: Create beautiful quicklook movies from the pixel data observed by NASA's Kepler spacecraft.
Home-page: http://barentsen.github.io/k2flix
Author: Geert Barentsen
Author-email: geert@barentsen.be
License: MIT
Platform: UNKNOWN
Classifier: Development Status :: 5 - Production/Stable
Classifier: License :: OSI Approved :: MIT License
Classifier: Operating System :: OS Independent
Classifier: Programming Language :: Python
Classifier: Intended Audience :: Science/Research
Classifier: Topic :: Scientific/Engineering :: Astronomy
Requires-Dist: numpy
Requires-Dist: matplotlib
Requires-Dist: astropy (>=0.4)
Requires-Dist: imageio (>=1)
